{"name":"build-javascript","namedChunkGroups":{"app":{"name":"app","assets":[{"name":"webpack-runtime-ae3d0e5b5cdadafb4410.js","size":4763},{"name":"framework-426047d00a237fdf4dab.js","size":140316},{"name":"app-97f544569dd2540c625f.js","size":67884}],"filteredAssets":0,"assetsSize":212963,"filteredAuxiliaryAssets":3,"auxiliaryAssetsSize":613273},"component---src-pages-index-tsx":{"name":"component---src-pages-index-tsx","assets":[{"name":"styles.e3a46e779f5f0b299d2e.css","size":9995},{"name":"component---src-pages-index-tsx-fb0a880201ef1ffecfd7.js","size":92709}],"filteredAssets":0,"assetsSize":102704,"filteredAuxiliaryAssets":24,"auxiliaryAssetsSize":870132}},"assetsByChunkName":{"app":["webpack-runtime-ae3d0e5b5cdadafb4410.js","framework-426047d00a237fdf4dab.js","app-97f544569dd2540c625f.js"],"component---src-pages-index-tsx":["styles.e3a46e779f5f0b299d2e.css","component---src-pages-index-tsx-fb0a880201ef1ffecfd7.js"]},"childAssetsByChunkName":{}}